components/component_flop.v
// Author - Shravan
////////////////////////
// Description
//   N bit flop 
///////////////////////

module component_flop
# ( parameter WIDTH = 1
)

(
  input  logic                clk,
  input  logic                rst_n,

  input  logic                valid_in,
  input  logic  [WIDTH-1 : 0] d_in,
  output logic  [WIDTH-1 : 0] d_out
);

  always @(posedge clk or negedge rst_n)
    if (~rst_n)
      d_out <= {WIDTH{1'b0}};
    else if (valid_in)
      d_out <= d_in;

endmodule

project_101detect/rtl/top.sv
/////////////////////////////////////////
//Description
//  101 sequence detector
/////////////////////////////////////////
//import top_pkg::*;

module top (
  input  logic        clk,
  input  logic        rst_n, 

  input  logic        data_in,
  output logic        sequence_detected
);

//Internal signals
//TODO : Check why SV pkg doesn't work with icarus. Is it working somewhere
//top_pkg::fsm_state_t state;
//top_pkg::fsm_state_t next_state;
//-----Error Segmentation fault (core dumped)
//

 localparam ST_IDLE    = 4'h0;
 localparam ST_1       = 4'h1;
 localparam ST_10      = 4'h2;
 localparam ST_101     = 4'h4;

 logic [2:0] state, next_state;

/////////////////////////
//Combinational logic
/////////////////////////
// next_state logic
always @(*) begin
  //default assignment to avoid latch inference
  next_state = state;

  case (state)
    ST_IDLE : next_state = data_in ? ST_1   : ST_IDLE;
    ST_1    : next_state = data_in ? ST_1   : ST_10;
    ST_10   : next_state = data_in ? ST_101 : ST_IDLE;
    ST_101  : next_state = data_in ? ST_1   : ST_10;
    default : next_state = state;
  endcase
end

assign sequence_detected = (state == ST_101);

/////////////////////////
//Sequential logic
/////////////////////////
component_flop #(.WIDTH(3)) u_state_ff  (
  .clk      (clk),
  .rst_n    (rst_n),
  .valid_in (1'b1),
  .d_in     (next_state),
  .d_out    (state)
);
/////////////////////////
//Sub block instantiations
/////////////////////////

/////////////////////////
//Assertions
/////////////////////////
endmodule

project_101detect/tb/top_tb.sv
module top_tb();

//internal signals
  logic        clk;
  logic        rst_n;
  logic        data_in;
  logic        sequence_detected;

//dut instantiation
  top u_top (
    .clk               (clk),
    .rst_n             (rst_n), 
    .data_in           (data_in),
    .sequence_detected (sequence_detected)
  );

//test
  initial begin
    clk     = 0; 
    rst_n   = 1;
    data_in = 0;
    #5
    rst_n = 0;
    #5
    rst_n = 1;
    @(posedge clk);//wait for clk event and start stimulus
    data_in = 0;
  
    @(posedge clk);
    data_in = 1;
  
    @(posedge clk);
    data_in = 0;
  
    @(posedge clk);
    data_in = 1;
  
    @(posedge clk);
    data_in = 0;
  
    @(posedge clk);
    data_in = 1;
  
    @(posedge clk);
    data_in = 1;
  
    @(posedge clk);
    data_in = 0;
  
    @(posedge clk);
    data_in = 1;
  
    @(posedge clk);
    @(posedge clk);
	  $finish;
  end
  
  always
  #5 clk = ~clk;

//wave dump
  initial begin
      $dumpfile("test.vcd");
      $dumpvars(0,top_tb); //tb top hieararchy ; after compilation run vvp ./a.out
   end
	
//monitors
	initial begin
		$monitor("Time = %t, data_in = %b, state = %b, sequence_detected=%b", $time, data_in, u_top.state,sequence_detected );
	end
	
endmodule

project_101detect/out/test.vcd
$date
	Sat Mar  4 16:42:13 2023
$end
$version
	Icarus Verilog
$end
$timescale
	1s
$end
$scope module top_tb $end
$var wire 1 ! sequence_detected $end
$var reg 1 " clk $end
$var reg 1 # data_in $end
$var reg 1 $ rst_n $end
$scope module u_top $end
$var wire 1 " clk $end
$var wire 1 # data_in $end
$var wire 1 $ rst_n $end
$var wire 3 % state [2:0] $end
$var wire 1 ! sequence_detected $end
$var reg 3 & next_state [2:0] $end
$scope module u_state_ff $end
$var wire 1 " clk $end
$var wire 3 ' d_in [2:0] $end
$var wire 1 $ rst_n $end
$var wire 1 ( valid_in $end
$var reg 3 ) d_out [2:0] $end
$upscope $end
$upscope $end
$upscope $end
$enddefinitions $end
#0
$dumpvars
bx )
1(
bx '
bx &
bx %
1$
0#
0"
x!
$end
#5
b0 &
b0 '
0!
b0 %
b0 )
1"
0$
#10
0"
1$
#15
1"
#20
0"
#25
b1 &
b1 '
1#
1"
#30
0"
#35
b1 %
b1 )
b10 &
b10 '
0#
1"
#40
0"
#45
b10 %
b10 )
b100 &
b100 '
1#
1"
#50
0"
#55
1!
b100 %
b100 )
b10 &
b10 '
0#
1"
#60
0"
#65
0!
b10 %
b10 )
b100 &
b100 '
1#
1"
#70
0"
#75
b1 &
b1 '
1!
b100 %
b100 )
1"
#80
0"
#85
0!
b1 %
b1 )
b10 &
b10 '
0#
1"
#90
0"
#95
b10 %
b10 )
b100 &
b100 '
1#
1"
#100
0"
#105
b1 &
b1 '
1!
b100 %
b100 )
1"
#110
0"
#115
0!
b1 %
b1 )
1"
